README.rst
setup.py
cognitive_sr/__init__.py
cognitive_sr/apiclient.py
cognitive_sr/identification.py
cognitive_sr/verification.py
ms_cognitive_speaker_recognition.egg-info/PKG-INFO
ms_cognitive_speaker_recognition.egg-info/SOURCES.txt
ms_cognitive_speaker_recognition.egg-info/dependency_links.txt
ms_cognitive_speaker_recognition.egg-info/requires.txt
ms_cognitive_speaker_recognition.egg-info/top_level.txt