Metadata-Version: 1.1
Name: ms-cognitive-speaker-recognition
Version: 0.1
Summary: API client for Microsoft Cognitive Services (Speaker Recognition)
Home-page: https://github.com/robladbrook/ms-cognitive-speaker-recognition
Author: Rob Ladbrook
Author-email: mscognitive@slyfx.com
License: MIT
Download-URL: https://github.com/robladbrook/ms-cognitive-speaker-recognition/tarball/0.1
Keywords: speaker,voice,microsoft,recognition,cognitive
Platform: UNKNOWN
Classifier: Development Status :: 5 - Production/Stable
Classifier: Intended Audience :: Developers
Classifier: Natural Language :: English
Classifier: License :: OSI Approved :: MIT License
Classifier: Programming Language :: Python
Classifier: Programming Language :: Python :: 2.6
Classifier: Programming Language :: Python :: 2.7
Classifier: Programming Language :: Python :: 3
Classifier: Programming Language :: Python :: 3.3
Classifier: Programming Language :: Python :: 3.4
Classifier: Programming Language :: Python :: 3.5
Classifier: Programming Language :: Python :: 3.6
